<?xml version="1.0" encoding="UTF-8" standalone="yes"?>
<sst xmlns="http://schemas.openxmlformats.org/spreadsheetml/2006/main" count="4216" uniqueCount="50"><si><t>Year</t></si><si><t>Gross Sales</t></si><si><t>Discounts</t></si><si><t>COGS</t></si><si><t>Units Sold</t></si><si><t>Manufacturing Price</t></si><si><t>Segment</t></si><si><t>Small Business</t></si><si><t>Midmarket</t></si><si><t>Enterprise</t></si><si><t>Government</t></si><si><t>Channel Partners</t></si><si><t>Date</t></si><si><t>Month Number</t></si><si><t>2013</t></si><si><t>2014</t></si><si><t>Canada</t></si><si><t>United States of America</t></si><si><t>France</t></si><si><t>Germany</t></si><si><t>Mexico</t></si><si><t>January</t></si><si><t>February</t></si><si><t>March</t></si><si><t>April</t></si><si><t>May</t></si><si><t>June</t></si><si><t>July</t></si><si><t>August</t></si><si><t>September</t></si><si><t>October</t></si><si><t>November</t></si><si><t>December</t></si><si><t>Profit</t></si><si><t xml:space="preserve"> Sales</t></si><si><t>Sale Price</t></si><si><t>Country</t></si><si><t>Product</t></si><si><t>Carretera</t></si><si><t>Montana</t></si><si><t>Paseo</t></si><si><t>Velo</t></si><si><t>VTT</t></si><si><t>Amarilla</t></si><si><t>Discount Band</t></si><si><t>None</t></si><si><t>Low</t></si><si><t>Medium</t></si><si><t>High</t></si><si><t>Month Name</t></si></sst>